cprotogen/__init__.py
cprotogen/generator.py
cprotogen/py.typed
cprotogen-0.1.0.dist-info/LICENSE
cprotogen-0.1.0.dist-info/METADATA
cprotogen-0.1.0.dist-info/WHEEL
cprotogen-0.1.0.dist-info/entry_points.txt
cprotogen-0.1.0.dist-info/top_level.txt
cprotogen-0.1.0.dist-info/RECORD
