Metadata-Version: 2.1
Name: cprotogen
Version: 0.1.0
Summary: A simple Python library and command-line tool for generating C function prototypes from source files.
Author: Matthias Cremieux
License: MIT License
Project-URL: Home, https://github.com/Mattcrmx/cprotogen
Requires-Python: >=3.11
License-File: LICENSE
Requires-Dist: pycparser
Requires-Dist: pycparser-fake-libc
Provides-Extra: dev
Requires-Dist: black; extra == "dev"
Requires-Dist: pre-commit; extra == "dev"
Requires-Dist: ruff; extra == "dev"
Provides-Extra: test
Requires-Dist: pytest; extra == "test"
